mailblock/__init__.py
mailblock/client.py
mailblock/email_builder.py
mailblock/exceptions.py
mailblock/types.py
mailblock/utils.py
mailblock-1.1.0.dist-info/LICENSE
mailblock-1.1.0.dist-info/METADATA
mailblock-1.1.0.dist-info/WHEEL
mailblock-1.1.0.dist-info/top_level.txt
mailblock-1.1.0.dist-info/RECORD
